{
  "definitionName" : "jepson:branding-jepson",
  "id" : "1ea2915d-c097-4fe1-9a70-bf7cb10803cb",
  "label" : "Jepson",
  "type" : "brandingSet",
  "values" : {
    "ActionColor" : "rgb(0, 82, 194)",
    "BorderColor" : "rgb(212, 212, 212)",
    "CardBackgroundColor" : "rgba(255, 255, 255, 0)",
    "CompanyLogo" : "/file-asset/logo?v=1",
    "DetailTextColor" : "rgba(0, 0, 0, 0.6)",
    "ErrorFontColor" : "rgb(255, 158, 158)",
    "HeaderFonts" : "VIC_Regular",
    "LinkColor" : "rgb(1, 26, 60)",
    "LoginBackgroundColor" : "rgb(244, 244, 244)",
    "LoginBackgroundImage" : "",
    "OverlayTextColor" : "rgb(255, 255, 255)",
    "PageBackgroundColor" : "rgb(229, 229, 229)",
    "PrimaryFont" : "VIC_Regular",
    "TextColor" : "rgb(1, 26, 60)",
    "TextTransformStyle" : "none",
    "_ActionColorDarker" : "#003c8f",
    "_ActionColorTrans" : "rgba(0, 82, 194, 0.9)",
    "_BackgroundColor1" : "rgb(209, 209, 209)",
    "_BackgroundColor2" : "rgb(168, 168, 168)",
    "_BackgroundColor3" : "rgb(107, 107, 107)",
    "_DxpPageBackgroundColor" : "rgb(229, 229, 229)",
    "_HoverColor" : "rgba(0, 82, 194, 0.05)",
    "_LinkColorDarker" : "#000914",
    "_NeutralColor" : "#ecebea",
    "_NeutralColor1" : "rgb(217, 215, 213)",
    "_NeutralColor2" : "rgb(178, 174, 170)",
    "_NeutralColor3" : "rgb(118, 113, 107)",
    "_NeutralForegroundColor" : "#000",
    "_NeutralForegroundColor1" : "#000",
    "_NeutralForegroundColor2" : "#000",
    "_NeutralForegroundColor3" : "#fff",
    "_OverlayTextColorShadow" : "#000",
    "_PrimaryAccentColor1" : "rgb(0, 65, 153)",
    "_PrimaryAccentColor2" : "rgb(0, 30, 72)",
    "_PrimaryAccentColor3" : "rgb(0, 0, 0)",
    "_PrimaryAccentForegroundColor1" : "rgb(255, 255, 255)",
    "_PrimaryAccentForegroundColor2" : "rgb(255, 255, 255)",
    "_PrimaryAccentForegroundColor3" : "rgb(255, 255, 255)",
    "_TextColor1" : "rgb(0, 9, 20)",
    "_TextColor2" : "rgb(0, 0, 0)",
    "_TextColor3" : "rgb(0, 0, 0)"
  }
}