{
  "appPageId" : "e841f6c0-3e2c-4657-b253-81adb470ae15",
  "componentName" : "siteforce:sldsOneColLayout",
  "id" : "8b9c4d42-b25a-40cb-8037-880a17b58900",
  "label" : "Forgot Password",
  "regions" : [ {
    "components" : [ {
      "componentAttributes" : {
        "richTextValue" : "<div style=\"text-align: center;\"><span style=\"font-size:22px\">PASSWORD RESET</span></div>"
      },
      "componentName" : "forceCommunity:richTextInline",
      "id" : "e5a50b17-c821-4521-96a1-c7081b2ec835",
      "renderPriority" : "NEUTRAL",
      "renditionMap" : { },
      "type" : "component"
    }, {
      "componentAttributes" : {
        "richTextValue" : "<div style=\"text-align: center;\">To reset your password, we'll need your username.<br/> We'll send password reset instructions to the email address associated with your account.</div>"
      },
      "componentName" : "forceCommunity:richTextInline",
      "id" : "d856a4ad-b29f-44ba-a52e-bedf3e7e19cd",
      "renderPriority" : "NEUTRAL",
      "renditionMap" : { },
      "type" : "component"
    }, {
      "componentAttributes" : {
        "checkEmailUrl" : "./CheckPasswordResetEmail",
        "submitButtonLabel" : "Reset Password",
        "usernameLabel" : "Username"
      },
      "componentName" : "salesforceIdentity:forgotPassword2",
      "id" : "ce66df62-ef3a-4efe-aa3c-6ec11b98427e",
      "renderPriority" : "NEUTRAL",
      "renditionMap" : { },
      "type" : "component"
    }, {
      "componentAttributes" : {
        "richTextValue" : "<div style=\"text-align: center;\"><a href=\"./\">Cancel</a></div>"
      },
      "componentName" : "forceCommunity:richTextInline",
      "id" : "fc5d4f6e-d856-4bd6-af85-a6d2fdca0207",
      "renderPriority" : "NEUTRAL",
      "renditionMap" : { },
      "type" : "component"
    } ],
    "id" : "8afab084-9fde-4964-b009-7ed0fd058a68",
    "regionName" : "content",
    "type" : "region"
  }, {
    "components" : [ {
      "componentAttributes" : {
        "customHeadTags" : "",
        "description" : "",
        "title" : "Forgot Password"
      },
      "componentName" : "forceCommunity:seoAssistant",
      "id" : "cbf97717-6587-4cca-9051-8c8673d697de",
      "renditionMap" : { },
      "type" : "component"
    } ],
    "id" : "86600d73-76ce-4529-b9f2-29d29c2f6300",
    "regionName" : "sfdcHiddenRegion",
    "type" : "region"
  } ],
  "themeLayoutType" : "6GeCvqFbh6JkAmgsNSjk7bb2ML42Pf",
  "type" : "view",
  "viewType" : "forgot-password"
}